MANIFEST.in
setup.cfg
setup.py
./CHANGELOG.md
./LICENSE.txt
./README.md
./requirements.txt
./utilbox.egg-info/SOURCES.txt
./utilbox.egg-info/dependency_links.txt
./utilbox.egg-info/requires.txt
./utilbox.egg-info/top_level.txt
utilbox/__conf__.py
utilbox/__init__.py
utilbox.egg-info/PKG-INFO
utilbox.egg-info/SOURCES.txt
utilbox.egg-info/dependency_links.txt
utilbox.egg-info/requires.txt
utilbox.egg-info/top_level.txt
utilbox/crypt_utils/__init__.py
utilbox/crypt_utils/crypt_utils.py
utilbox/database_utils/__init__.py
utilbox/database_utils/mysql_utils.py
utilbox/database_utils/sql_utils.py
utilbox/json_utils/__init__.py
utilbox/json_utils/json_utils.py
utilbox/mail_utils/__init__.py
utilbox/mail_utils/mail_utils.py
utilbox/number_utils/__init__.py
utilbox/number_utils/number_utils.py
utilbox/os_utils/__init__.py
utilbox/os_utils/dir_utils.py
utilbox/os_utils/file_utils.py
utilbox/os_utils/sys_utils.py
utilbox/spreadsheet_utils/__init__.py
utilbox/spreadsheet_utils/csv_utils.py
utilbox/spreadsheet_utils/excel_utils.py
utilbox/string_utils/__init__.py
utilbox/string_utils/string_utils.py
utilbox/string_utils/text_utils.py