Metadata-Version: 1.1
Name: utilbox
Version: 0.1.6
Summary: Collection of utility packages for Python.
Home-page: https://github.com/jensonjose/utilbox
Author: Jenson Jose
Author-email: jensonjose@live.in
License: MIT
Platform: Any
Classifier: Development Status :: 3 - Alpha
Classifier: Environment :: Console
Classifier: Intended Audience :: Developers
Classifier: License :: OSI Approved :: MIT License
Classifier: Natural Language :: English
Classifier: Operating System :: OS Independent
Classifier: Programming Language :: Python :: 2.7
Classifier: Topic :: Software Development
Classifier: Topic :: Software Development :: Libraries :: Python Modules
Classifier: Topic :: Utilities
